odoo8_addon_hr_worked_days_from_timesheet-8.0.1.0.0.99.dev13-py2.7-nspkg.pth
odoo8_addon_hr_worked_days_from_timesheet-8.0.1.0.0.99.dev13.dist-info/DESCRIPTION.rst
odoo8_addon_hr_worked_days_from_timesheet-8.0.1.0.0.99.dev13.dist-info/METADATA
odoo8_addon_hr_worked_days_from_timesheet-8.0.1.0.0.99.dev13.dist-info/RECORD
odoo8_addon_hr_worked_days_from_timesheet-8.0.1.0.0.99.dev13.dist-info/WHEEL
odoo8_addon_hr_worked_days_from_timesheet-8.0.1.0.0.99.dev13.dist-info/metadata.json
odoo8_addon_hr_worked_days_from_timesheet-8.0.1.0.0.99.dev13.dist-info/namespace_packages.txt
odoo8_addon_hr_worked_days_from_timesheet-8.0.1.0.0.99.dev13.dist-info/top_level.txt
odoo_addons/hr_worked_days_from_timesheet/README.rst
odoo_addons/hr_worked_days_from_timesheet/__init__.py
odoo_addons/hr_worked_days_from_timesheet/__openerp__.py
odoo_addons/hr_worked_days_from_timesheet/i18n/de.po
odoo_addons/hr_worked_days_from_timesheet/i18n/es.po
odoo_addons/hr_worked_days_from_timesheet/i18n/fr.po
odoo_addons/hr_worked_days_from_timesheet/i18n/hr_worked_days_from_timesheet.pot
odoo_addons/hr_worked_days_from_timesheet/i18n/sl.po
odoo_addons/hr_worked_days_from_timesheet/models/__init__.py
odoo_addons/hr_worked_days_from_timesheet/models/hr_payslip.py
odoo_addons/hr_worked_days_from_timesheet/models/hr_payslip_worked_days.py
odoo_addons/hr_worked_days_from_timesheet/static/description/icon.png
odoo_addons/hr_worked_days_from_timesheet/tests/__init__.py
odoo_addons/hr_worked_days_from_timesheet/tests/test_worked_days_from_timesheet.py
odoo_addons/hr_worked_days_from_timesheet/views/hr_payslip_view.xml
